nagra_network_cloudflare_utils/__init__.py
nagra_network_cloudflare_utils/__main__.py
nagra_network_cloudflare_utils/compliance.py
nagra_network_cloudflare_utils/dns_checker.py
nagra_network_cloudflare_utils/list_zones.py
nagra_network_cloudflare_utils/schema.py
nagra_network_cloudflare_utils/schema_utils.py
nagra_network_cloudflare_utils-0.2.13.dist-info/METADATA
nagra_network_cloudflare_utils-0.2.13.dist-info/WHEEL
nagra_network_cloudflare_utils-0.2.13.dist-info/entry_points.txt
nagra_network_cloudflare_utils-0.2.13.dist-info/RECORD
