Metadata-Version: 2.3
Name: nagra-network-cloudflare-utils
Version: 0.2.13
Summary: 
Author: David Gallay
Author-email: david.gallay@nagra.com
Requires-Python: >=3.9,<4.0
Classifier: Programming Language :: Python :: 3
Classifier: Programming Language :: Python :: 3.9
Classifier: Programming Language :: Python :: 3.10
Classifier: Programming Language :: Python :: 3.11
Classifier: Programming Language :: Python :: 3.12
Classifier: Programming Language :: Python :: 3.13
Requires-Dist: click (>=8.1.7,<9.0.0)
Requires-Dist: cloudflare (>=3.1.1,<4.0.0)
Requires-Dist: glom (>=23.5.0,<24.0.0)
Requires-Dist: nagra-network-misc-utils (==0.2.7)
Requires-Dist: pydantic (>=2.9.2,<3.0.0)
